{
  "name": "Edge",
  "org": "arch-systems",
  "description": "Smart Edge Device - No Web/Mobile Support",
  "project_template": "default-template-v1-0-0",
  "variable_templates": [],
  "display_widget_templates": [],
  "report_processing_engine_ver": 2,
  "ui_extra": {
    "web": {
      "pageTemplateSlug": "proto"
    },
    "mobile": {
      "template": "default",
      "controller": "defaultCtrl",
      "other": null,
      "ioInfo": null
    }
  },
  "major_version": 1,
  "minor_version": 0,
  "patch_version": 0
}
